babilim/__init__.py
babilim/core/__init__.py
babilim/core/annotations.py
babilim/core/checkpoint.py
babilim/core/config.py
babilim/core/device.py
babilim/core/gradient_tape.py
babilim/core/gradient_tape_pt.py
babilim/core/gradient_tape_tf.py
babilim/core/itensor.py
babilim/core/logging.py
babilim/core/module.py
babilim/core/module_native.py
babilim/core/tensor.py
babilim/core/tensor_pt.py
babilim/core/tensor_tf.py
babilim/core/tmath/__init__.py
babilim/core/tmath/pytorch.py
babilim/core/tmath/tf.py
babilim/data/__init__.py
babilim/data/dataloader.py
babilim/data/dataset.py
babilim/data/image_grid.py
babilim/data/keras.py
babilim/data/pytorch.py
babilim/data/tfrecord.py
babilim/data/transformer.py
babilim/data/datasets/__init__.py
babilim/data/datasets/coco.py
babilim/data/specialized_readers/__init__.py
babilim/data/specialized_readers/binary_reader.py
babilim/data/specialized_readers/data_downloader.py
babilim/data/specialized_readers/multi_tar_reader.py
babilim/data/specialized_readers/multi_zip_reader.py
babilim/model/__init__.py
babilim/model/imagenet.py
babilim/model/sequential.py
babilim/model/layers/__init__.py
babilim/model/layers/activation.py
babilim/model/layers/batch_normalization.py
babilim/model/layers/convolution.py
babilim/model/layers/flatten.py
babilim/model/layers/fully_connected.py
babilim/model/layers/native_wrapper.py
babilim/model/layers/pooling.py
babilim/model/layers/reshape.py
babilim/model/layers/roi_ops.py
babilim/model/layers/selection.py
babilim/model/layers/tensor_combiners.py
babilim/training/__init__.py
babilim/training/losses.py
babilim/training/supervised.py
babilim/training/trainer.py
babilim/training/callbacks/__init__.py
babilim/training/callbacks/base_callback.py
babilim/training/callbacks/checkpoint_callback.py
babilim/training/callbacks/log_callback.py
babilim/training/callbacks/lr_update_callback.py
babilim/training/callbacks/tensorboard_callback.py
babilim/training/optimizers/__init__.py
babilim-20201011.dist-info/LICENSE
babilim-20201011.dist-info/METADATA
babilim-20201011.dist-info/WHEEL
babilim-20201011.dist-info/dependency_links.txt
babilim-20201011.dist-info/top_level.txt
babilim-20201011.dist-info/RECORD
