Metadata-Version: 2.1
Name: babilim
Version: 20201011
Summary: A try to unify the deep learning frameworks under one api.
Home-page: https://github.com/penguinmenac3/babilim
Author: Michael Fuerst
Author-email: mail@michaelfuerst.de
License: BSD
Download-URL: https://github.com/penguinmenac3/babilim/tarball/20201011
Platform: UNKNOWN
Classifier: Development Status :: 3 - Alpha
Classifier: Intended Audience :: Developers
Classifier: Programming Language :: Python
Requires-Dist: numpy
Requires-Dist: entangle-python
Requires-Dist: matplotlib
Requires-Dist: scipy
Requires-Dist: tensorboardX
Requires-Dist: packaging
